{"39514": {"recipe_name": "Basic Poutine Recipe", "recipe_url": "https://www.geniuskitchen.com/recipe/basic-poutine-recipe-39514", "recipe_ingredients": [{"ingredients_section": {"section_name": "", "ingredients": [{"ingredient": {"quantity": "", "measurement": "cooked", "name": "French fries", "details": ""}}, {"ingredient": {"quantity": "", "measurement": "", "name": "cheese curds (farmer cheese or \"squeaky cheese\")", "details": ""}}, {"ingredient": {"quantity": "", "measurement": "", "name": "beef gravy", "details": ""}}]}}], "recipe_steps": [{"steps_section": {"name": "", "steps": ["Mix French fries and cheese curds.", "Pour the gravy over top and wait until the cheese begins to melt.", "Then dig in."]}}]}}